typing_inspect_lib/__init__.py
typing_inspect_lib/core/__init__.py
typing_inspect_lib/core/get_args.py
typing_inspect_lib/core/get_base_type.py
typing_inspect_lib/core/get_origins.py
typing_inspect_lib/core/get_parameters.py
typing_inspect_lib/core/get_type_info.py
typing_inspect_lib/core/get_typing.py
typing_inspect_lib/core/helpers/__init__.py
typing_inspect_lib/core/helpers/compatibility.py
typing_inspect_lib/core/helpers/helpers.py
typing_inspect_lib/core/helpers/links.py
typing_inspect_lib/extras/__init__.py
typing_inspect_lib/extras/get_bases.py
typing_inspect_lib/extras/get_mro.py
typing_inspect_lib/extras/get_mro_orig.py
typing_inspect_lib/extras/get_parents.py
typing_inspect_lib/extras/get_type_var_info.py
typing_inspect_lib-0.0.1.dist-info/LICENSE
typing_inspect_lib-0.0.1.dist-info/METADATA
typing_inspect_lib-0.0.1.dist-info/WHEEL
typing_inspect_lib-0.0.1.dist-info/top_level.txt
typing_inspect_lib-0.0.1.dist-info/RECORD
