Metadata-Version: 2.1
Name: typing-inspect-lib
Version: 0.0.1
Summary: Type inspections for Python
Home-page: https://github.com/Peilonrayz/typing_inspect_lib
Author: Peilonrayz
Author-email: peilonrayz@gmail.com
License: MIT
Keywords: typing function annotations type hints hinting checking checker typehints typehinting typechecking inspect reflection introspection
Platform: UNKNOWN
Classifier: Development Status :: 3 - Alpha
Classifier: Environment :: Console
Classifier: Intended Audience :: Developers
Classifier: License :: OSI Approved :: MIT License
Classifier: Operating System :: OS Independent
Classifier: Programming Language :: Python :: 2
Classifier: Programming Language :: Python :: 2.7
Classifier: Programming Language :: Python :: 3
Classifier: Programming Language :: Python :: 3.4
Classifier: Programming Language :: Python :: 3.5
Classifier: Programming Language :: Python :: 3.6
Classifier: Programming Language :: Python :: 3.7
Classifier: Topic :: Software Development
Requires-Dist: typing (>=3.6.1) ; python_version < "3.5"
Provides-Extra: extensions
Requires-Dist: typing-extensions ; extra == 'extensions'
